{
  "spdxVersion": "SPDX-2.3",
  "dataLicense": "CC0-1.0",
  "SPDXID": "SPDXRef-DOCUMENT",
  "name": "com.github.PepperCode1/Continuity",
  "documentNamespace": "https://spdx.org/spdxdocs/protobom/d6814d66-8bd8-427e-9a3d-84b02baa3912",
  "creationInfo": {
    "creators": [
      "Tool: protobom-v0.0.0-20251201163737-0a89483e840c+dirty",
      "Tool: GitHub.com-Dependency-Graph"
    ],
    "created": "2025-12-08T11:58:35Z"
  },
  "packages": [
    {
      "name": "actions/checkout",
      "SPDXID": "SPDXRef-githubactions-actions-checkout-4..-75c946",
      "versionInfo": "4.*.*",
      "downloadLocation": "NOASSERTION",
      "filesAnalyzed": false,
      "externalRefs": [
        {
          "referenceCategory": "PACKAGE-MANAGER",
          "referenceType": "purl",
          "referenceLocator": "pkg:githubactions/actions/checkout@4.%2A.%2A"
        }
      ]
    },
    {
      "name": "actions/upload-artifact",
      "SPDXID": "SPDXRef-githubactions-actions-upload-artifact-4..-75c946",
      "versionInfo": "4.*.*",
      "downloadLocation": "NOASSERTION",
      "filesAnalyzed": false,
      "externalRefs": [
        {
          "referenceCategory": "PACKAGE-MANAGER",
          "referenceType": "purl",
          "referenceLocator": "pkg:githubactions/actions/upload-artifact@4.%2A.%2A"
        }
      ]
    },
    {
      "name": "actions/setup-java",
      "SPDXID": "SPDXRef-githubactions-actions-setup-java-4..-75c946",
      "versionInfo": "4.*.*",
      "downloadLocation": "NOASSERTION",
      "filesAnalyzed": false,
      "externalRefs": [
        {
          "referenceCategory": "PACKAGE-MANAGER",
          "referenceType": "purl",
          "referenceLocator": "pkg:githubactions/actions/setup-java@4.%2A.%2A"
        }
      ]
    },
    {
      "name": "gradle/actions/setup-gradle",
      "SPDXID": "SPDXRef-githubactions-gradleactions-setup-gradle-5..-75c946",
      "versionInfo": "5.*.*",
      "downloadLocation": "NOASSERTION",
      "filesAnalyzed": false,
      "externalRefs": [
        {
          "referenceCategory": "PACKAGE-MANAGER",
          "referenceType": "purl",
          "referenceLocator": "pkg:githubactions/gradle/actions/setup-gradle@5.%2A.%2A"
        }
      ]
    },
    {
      "name": "com.github.PepperCode1/Continuity",
      "SPDXID": "SPDXRef-github-PepperCode1-Continuity-1.20.1dev-6cd1cf",
      "versionInfo": "1.20.1/dev",
      "downloadLocation": "git+https://github.com/PepperCode1/Continuity",
      "filesAnalyzed": false,
      "licenseDeclared": "LGPL-3.0",
      "externalRefs": [
        {
          "referenceCategory": "PACKAGE-MANAGER",
          "referenceType": "purl",
          "referenceLocator": "pkg:github/PepperCode1/Continuity@1.20.1%2Fdev"
        }
      ]
    }
  ],
  "relationships": [
    {
      "spdxElementId": "SPDXRef-github-PepperCode1-Continuity-1.20.1dev-6cd1cf",
      "relatedSpdxElement": "SPDXRef-githubactions-gradleactions-setup-gradle-5..-75c946",
      "relationshipType": "DEPENDS_ON"
    },
    {
      "spdxElementId": "SPDXRef-github-PepperCode1-Continuity-1.20.1dev-6cd1cf",
      "relatedSpdxElement": "SPDXRef-githubactions-actions-checkout-4..-75c946",
      "relationshipType": "DEPENDS_ON"
    },
    {
      "spdxElementId": "SPDXRef-github-PepperCode1-Continuity-1.20.1dev-6cd1cf",
      "relatedSpdxElement": "SPDXRef-githubactions-actions-upload-artifact-4..-75c946",
      "relationshipType": "DEPENDS_ON"
    },
    {
      "spdxElementId": "SPDXRef-github-PepperCode1-Continuity-1.20.1dev-6cd1cf",
      "relatedSpdxElement": "SPDXRef-githubactions-actions-setup-java-4..-75c946",
      "relationshipType": "DEPENDS_ON"
    },
    {
      "spdxElementId": "SPDXRef-DOCUMENT",
      "relatedSpdxElement": "SPDXRef-github-PepperCode1-Continuity-1.20.1dev-6cd1cf",
      "relationshipType": "DESCRIBES"
    }
  ]
}